stam-0.12.1.dist-info/METADATA
stam-0.12.1.dist-info/WHEEL
stam-0.12.1.dist-info/licenses/LICENSE
stam/__init__.py
stam/__init__.pyi
stam/py.typed
stam/stam.cpython-311-x86_64-linux-gnu.so
stam-0.12.1.dist-info/RECORD
