Metadata-Version: 2.4
Name: stam
Version: 0.12.1
Requires-Dist: pytest ; extra == 'test'
Provides-Extra: test
License-File: LICENSE
Home-Page: https://annotation.github.io/stam
